LICENSE
MANIFEST
MANIFEST.in
README.md
pyproject.toml
requirements.txt
setup.cfg
setup.py
phunspell/__init__.py
phunspell/phunspell.py
phunspell.egg-info/PKG-INFO
phunspell.egg-info/SOURCES.txt
phunspell.egg-info/dependency_links.txt
phunspell.egg-info/requires.txt
phunspell.egg-info/top_level.txt
phunspell/data/dictionary/af_ZA/af_ZA.aff
phunspell/data/dictionary/af_ZA/af_ZA.dic
phunspell/data/dictionary/an_ES/an_ES.aff
phunspell/data/dictionary/an_ES/an_ES.dic
phunspell/data/dictionary/ar/ar.aff
phunspell/data/dictionary/ar/ar.dic
phunspell/data/dictionary/be_BY/be_BY.aff
phunspell/data/dictionary/be_BY/be_BY.dic
phunspell/data/dictionary/bg_BG/bg_BG.aff
phunspell/data/dictionary/bg_BG/bg_BG.dic
phunspell/data/dictionary/bn_BD/bn_BD.aff
phunspell/data/dictionary/bn_BD/bn_BD.dic
phunspell/data/dictionary/bo/bo.aff
phunspell/data/dictionary/bo/bo.dic
phunspell/data/dictionary/br_FR/br_FR.aff
phunspell/data/dictionary/br_FR/br_FR.dic
phunspell/data/dictionary/bs_BA/bs_BA.aff
phunspell/data/dictionary/bs_BA/bs_BA.dic
phunspell/data/dictionary/ca/ca-valencia.aff
phunspell/data/dictionary/ca/ca-valencia.dic
phunspell/data/dictionary/ca/ca.aff
phunspell/data/dictionary/ca/ca.dic
phunspell/data/dictionary/cs_CZ/cs_CZ.aff
phunspell/data/dictionary/cs_CZ/cs_CZ.dic
phunspell/data/dictionary/da_DK/da_DK.aff
phunspell/data/dictionary/da_DK/da_DK.dic
phunspell/data/dictionary/de/de_AT.aff
phunspell/data/dictionary/de/de_AT.dic
phunspell/data/dictionary/de/de_CH.aff
phunspell/data/dictionary/de/de_CH.dic
phunspell/data/dictionary/de/de_DE.aff
phunspell/data/dictionary/de/de_DE.dic
phunspell/data/dictionary/el_GR/el_GR.aff
phunspell/data/dictionary/el_GR/el_GR.dic
phunspell/data/dictionary/en/en_AU.aff
phunspell/data/dictionary/en/en_AU.dic
phunspell/data/dictionary/en/en_CA.aff
phunspell/data/dictionary/en/en_CA.dic
phunspell/data/dictionary/en/en_GB.aff
phunspell/data/dictionary/en/en_GB.dic
phunspell/data/dictionary/en/en_US.aff
phunspell/data/dictionary/en/en_US.dic
phunspell/data/dictionary/en/en_ZA.aff
phunspell/data/dictionary/en/en_ZA.dic
phunspell/data/dictionary/es/es.aff
phunspell/data/dictionary/es/es.dic
