Metadata-Version: 2.1
Name: phunspell
Version: 0.1.2
Summary: Pure Python spell checker, utilizing Spylls a port of Hunspell
Home-page: https://github.com/dvwright/phunspell
Author: David Wright
Author-email: dvwright@cpan.org
License: MIT
Download-URL: https://github.com/dvwright/phunspell/archive/v0.1.2.tar.gz
Keywords: Spelling,Hunspell,Spylls,Python
Platform: UNKNOWN
Classifier: Development Status :: 4 - Beta
Classifier: Intended Audience :: Developers
Classifier: Topic :: Software Development :: Libraries :: Python Modules
Classifier: License :: OSI Approved :: MIT License
Classifier: Programming Language :: Python :: 2.7
Classifier: Programming Language :: Python :: 3
Classifier: Programming Language :: Python :: 3.4
Classifier: Programming Language :: Python :: 3.5
Classifier: Programming Language :: Python :: 3.6
Classifier: Programming Language :: Python :: 3.7
Classifier: Programming Language :: Python :: 3.8
